simplehdlc/__init__.py
simplehdlc-0.1.0.dist-info/LICENSE
simplehdlc-0.1.0.dist-info/METADATA
simplehdlc-0.1.0.dist-info/WHEEL
simplehdlc-0.1.0.dist-info/top_level.txt
simplehdlc-0.1.0.dist-info/RECORD
