Metadata-Version: 2.1
Name: simplehdlc
Version: 0.1.0
Summary: A python implementation of the simplehdlc packet encoder/parser
Home-page: https://github.com/jeremyherbert/python-simplehdlc
Author: Jeremy Herbert
Author-email: jeremy.006@gmail.com
License: UNKNOWN
Platform: UNKNOWN
Classifier: Programming Language :: Python :: 3
Classifier: License :: OSI Approved :: MIT License
Classifier: Operating System :: OS Independent
Requires-Python: >=3.6
